iot_kernel/__init__.py
iot_kernel/__main__.py
iot_kernel/install.py
iot_kernel/kernel.py
iot_kernel/kernel_logger.py
iot_kernel/nb_conf.py
iot_kernel/version.py
iot_kernel/images/logo-32x32.png
iot_kernel/images/logo-64x64.png
iot_kernel/magics/__init__.py
iot_kernel/magics/bash.py
iot_kernel/magics/connect.py
iot_kernel/magics/debugging.py
iot_kernel/magics/discover.py
iot_kernel/magics/file_ops.py
iot_kernel/magics/magic.py
iot_kernel/magics/mcu.py
iot_kernel/magics/micropip.py
iot_kernel/magics/pip.py
iot_kernel/magics/rsync.py
iot_kernel/magics/ssh.py
iot_kernel/magics/store.py
iot_kernel/magics/utilities.py
iot_kernel-0.5.28.dist-info/LICENSE
iot_kernel-0.5.28.dist-info/METADATA
iot_kernel-0.5.28.dist-info/WHEEL
iot_kernel-0.5.28.dist-info/top_level.txt
iot_kernel-0.5.28.dist-info/zip-safe
iot_kernel-0.5.28.dist-info/RECORD
